{
  "replace": false,
  "values": [
    {
      "id": "minecraft:honeycomb_block",
      "required": true
    },
    {
      "id": "the_bumblezone:porous_honeycomb_block",
      "required": true
    },
    {
      "id": "the_bumblezone:filled_porous_honeycomb_block",
      "required": true
    },
    {
      "id": "the_bumblezone:empty_honeycomb_brood_block",
      "required": true
    },
    {
      "id": "the_bumblezone:honeycomb_brood_block",
      "required": true
    },
    {
      "id": "#forge:storage_blocks/honeycombs",
      "required": false
    },
    {
      "id": "productivebees:configurable_comb",
      "required": false
    },
    {
      "id": "buzzier_bees:crystallized_honey_block",
      "required": false
    },
    {
      "id": "buzzier_bees:honeycomb_tiles",
      "required": false
    }
  ]
}