{
  "required": true,
  "package": "net.telepathicgrunt.bumblezone.mixin",
  "compatibilityLevel": "JAVA_8",
  "mixins": [
    "BeeEntityInvoker",
    "BlockOverlayRendererMixin",
    "BucketItemAccessor",
    "ClientPlayerRightClickMixin",
    "ClientWorldMixin",
    "DispenserAccessor",
    "EnderpearlImpactMixin",
    "HoneyDrinkMixin",
    "HoneyPickupMixin",
    "MobHitMixin",
    "MobSpawnLocationMixin",
    "MobTickMixin",
    "PlayerDamagedMixin",
    "PlayerDamageShieldInvoker",
    "PlayerDimensionChangeMixin",
    "PlayerHiveWrathTickMixin",
    "PlayerInteractsEntityMixin",
    "PlayerTeleportationTickMixin",
    "PollenedBeeNaturalSpawnMixin",
    "RedstoneDustCanConnectMixin",
    "ServerPlayerRightClickMixin",
    "StructureAccessor",
    "WaterEquivalenceMixin"
  ],
  "client": [
  ],
  "injectors": {
    "defaultRequire": 1
  }
}
