{
  "type": "minecraft:archaeology",
  "random_sequence": "the_bumblezone:archaeology",
  "pools": [
    {
      "rolls": 1,
      "bonus_rolls": 0.0,
      "entries": [
        {
          "name": "minecraft:brewer_pottery_sherd",
          "type": "minecraft:item",
          "weight": 2
        },
        {
          "name": "minecraft:explorer_pottery_sherd",
          "type": "minecraft:item",
          "weight": 2
        },
        {
          "name": "minecraft:shelter_pottery_sherd",
          "type": "minecraft:item",
          "weight": 2
        },
        {
          "name": "minecraft:angler_pottery_sherd",
          "type": "minecraft:item",
          "weight": 2
        },
        {
          "name": "minecraft:amethyst_shard",
          "type": "minecraft:item",
          "weight": 2
        },
        {
          "name": "minecraft:tipped_arrow",
          "type": "minecraft:item",
          "weight": 2,
          "functions": [
            {
              "function": "minecraft:set_nbt",
              "tag": "{Potion:\"minecraft:poison\"}"
            }
          ]
        },
        {
          "name": "minecraft:fishing_rod",
          "type": "minecraft:item",
          "weight": 2
        },
        {
          "name": "minecraft:spider_eye",
          "type": "minecraft:item",
          "weight": 2
        },
        {
          "name": "minecraft:bone",
          "type": "minecraft:item",
          "weight": 2
        },
        {
          "name": "minecraft:skeleton_skull",
          "type": "minecraft:item",
          "weight": 2
        },
        {
          "name": "minecraft:flower_banner_pattern",
          "type": "minecraft:item",
          "weight": 1
        },
        {
          "name": "minecraft:wayfinder_armor_trim_smithing_template",
          "type": "minecraft:item",
          "weight": 1
        },
        {
          "name": "the_bumblezone:buzzing_briefcase",
          "type": "minecraft:item",
          "weight": 1
        }
      ]
    }
  ]
}