{
  "parent": "the_bumblezone:the_bumblezone/honey_crystal/honey_crystal_shield_block_ineffectively",
  "display": {
    "icon": {
      "item": "the_bumblezone:honey_crystal_shield"
    },
    "title": {
      "translate": "advancements.the_bumblezone.obtain_maxed_honey_crystal_shield.title"
    },
    "description": {
      "translate": "advancements.the_bumblezone.obtain_maxed_honey_crystal_shield.description"
    },
    "frame": "challenge",
    "show_toast": true,
    "announce_to_chat": true,
    "hidden": false
  },
  "rewards": {
    "experience": 2000
  },
  "criteria": {
    "obtain_maxed_honey_crystal_shield": {
      "trigger": "minecraft:inventory_changed",
      "conditions": {
        "items": [
          {
            "item": "the_bumblezone:honey_crystal_shield",
            "nbt": "{\"RepairCost\":63}"
          }
        ]
      }
    }
  },
  "requirements": [
    [
      "obtain_maxed_honey_crystal_shield"
    ]
  ]
}