{
  "type": "the_bumblezone:incense_candle_recipe",
  "category": "misc",
  "group": "the_bumblezone:string_curtain",
  "pattern": [
    "s",
    "h",
    "h"
  ],
  "key": {
    "h": {
      "tag": "the_bumblezone:carvable_wax"
    },
    "s": {
      "item": "minecraft:string"
    }
  },
  "shapelessExtraIngredients": [
    {
      "item": "the_bumblezone:royal_jelly_bottle"
    }
  ],
  "maxAllowedPotions": 5,
  "allowNormalPotions": true,
  "allowSplashPotions": true,
  "allowLingeringPotions": true,
  "maxLevelCap": 5,
  "resultCount": 1
}